Workbook

Sheet Sheet1
A1: Transaction_ID | B1: Date | C1: Customer_ID | D1: Customer_Name | E1: Product_ID | F1: Product_Name | G1: Category | H1: Quantity | I1: Unit_Price | J1: Payment_Method | K1: Region | L1: Customer_Segment | M1: Customer_Since | N1: Total_Amount | O1: Current Date | P1: Current Timestamp | Q1: Date Difference | R1: End of Month | T1: FILTER
A2: TRX0154 | B2: 45459 | C2: CUST023 | D2: Paul Baker | E2: P001 | F2: Laptop | G2: Electronics | H2: 5 | I2: 899.99 | J2: Credit Card | K2: South | L2: Standard | M2: 44974 | N2: =I2*H2 -> 4499.95 | O2: =TODAY() -> 46143 | P2: =NOW() -> 46143.958 | Q2: =DATEDIF(M2,B2,"D") -> 485 | R2: =EOMONTH(B2,0) -> 45473 | T2: {=_xlfn._xlws.FILTER(K:K,(K:K=K6)+(K:K=K3),"Region Not Found")} -> East
A3: TRX0044 | B3: 45459 | C3: CUST029 | D3: Edward Mitchell | E3: P001 | F3: Laptop | G3: Electronics | H3: 5 | I3: 899.99 | J3: PayPal | K3: East | L3: Premium | M3: 45278 | N3: =I3*H3 -> 4499.95 | O3: =TODAY() -> 46143 | P3: =NOW() -> 46143.958 | Q3: =DATEDIF(M3,B3,"D") -> 181 | R3: =EOMONTH(B3,0) -> 45473 | T3: East
A4: TRX0244 | B4: 45497 | C4: CUST013 | D4: Joseph Jackson | E4: P001 | F4: Laptop | G4: Electronics | H4: 5 | I4: 899.99 | J4: Debit Card | K4: South | L4: Standard | M4: 44899 | N4: =I4*H4 -> 4499.95 | O4: =TODAY() -> 46143 | P4: =NOW() -> 46143.958 | Q4: =DATEDIF(M4,B4,"D") -> 598 | R4: =EOMONTH(B4,0) -> 45504 | T4: East
A5: TRX0132 | B5: 45523 | C5: CUST047 | D5: Gerald Murphy | E5: P001 | F5: Laptop | G5: Electronics | H5: 5 | I5: 899.99 | J5: Debit Card | K5: East | L5: Basic | M5: 44526 | N5: =I5*H5 -> 4499.95 | O5: =TODAY() -> 46143 | P5: =NOW() -> 46143.958 | Q5: =DATEDIF(M5,B5,"D") -> 997 | R5: =EOMONTH(B5,0) -> 45535 | T5: East
A6: TRX0163 | B6: 45645 | C6: CUST019 | D6: Daniel King | E6: P001 | F6: Laptop | G6: Electronics | H6: 5 | I6: 899.99 | J6: Debit Card | K6: East | L6: Standard | M6: 44625 | N6: =I6*H6 -> 4499.95 | O6: =TODAY() -> 46143 | P6: =NOW() -> 46143.958 | Q6: =DATEDIF(M6,B6,"D") -> 1020 | R6: =EOMONTH(B6,0) -> 45657 | T6: East
A7: TRX0016 | B7: 45724 | C7: CUST035 | D7: Harry Morgan | E7: P001 | F7: Laptop | G7: Electronics | H7: 5 | I7: 899.99 | J7: PayPal | K7: East | L7: Premium | M7: 45389 | N7: =I7*H7 -> 4499.95 | O7: =TODAY() -> 46143 | P7: =NOW() -> 46143.958 | Q7: =DATEDIF(M7,B7,"D") -> 335 | R7: =EOMONTH(B7,0) -> 45747 | T7: East
A8: TRX0122 | B8: 45410 | C8: CUST025 | D8: Mark Carter | E8: P001 | F8: Laptop | G8: Electronics | H8: 4 | I8: 899.99 | J8: Credit Card | K8: West | L8: Standard | M8: 45327 | N8: =I8*H8 -> 3599.96 | O8: =TODAY() -> 46143 | P8: =NOW() -> 46143.958 | Q8: =DATEDIF(M8,B8,"D") -> 83 | R8: =EOMONTH(B8,0) -> 45412 | T8: East
A9: TRX0104 | B9: 45471 | C9: CUST012 | D9: Patricia Moore | E9: P001 | F9: Laptop | G9: Electronics | H9: 4 | I9: 899.99 | J9: Credit Card | K9: East | L9: Premium | M9: 44993 | N9: =I9*H9 -> 3599.96 | O9: =TODAY() -> 46143 | P9: =NOW() -> 46143.958 | Q9: =DATEDIF(M9,B9,"D") -> 478 | R9: =EOMONTH(B9,0) -> 45473 | T9: East
A10: TRX0249 | B10: 45504 | C10: CUST030 | D10: Helen Roberts | E10: P001 | F10: Laptop | G10: Electronics | H10: 4 | I10: 899.99 | J10: Debit Card | K10: South | L10: Standard | M10: 44523 | N10: =I10*H10 -> 3599.96 | O10: =TODAY() -> 46143 | P10: =NOW() -> 46143.958 | Q10: =DATEDIF(M10,B10,"D") -> 981 | R10: =EOMONTH(B10,0) -> 45504 | T10: East
A11: TRX0030 | B11: 45686 | C11: CUST011 | D11: William White | E11: P001 | F11: Laptop | G11: Electronics | H11: 4 | I11: 899.99 | J11: PayPal | K11: Central | L11: Basic | M11: 44734 | N11: =I11*H11 -> 3599.96 | O11: =TODAY() -> 46143 | P11: =NOW() -> 46143.958 | Q11: =DATEDIF(M11,B11,"D") -> 952 | R11: =EOMONTH(B11,0) -> 45688 | T11: East
A12: TRX0231 | B12: 45412 | C12: CUST018 | D12: Barbara Young | E12: P002 | F12: Smartphone | G12: Electronics | H12: 5 | I12: 699.99 | J12: Cash | K12: West | L12: Basic | M12: 45167 | N12: =I12*H12 -> 3499.95 | O12: =TODAY() -> 46143 | P12: =NOW() -> 46143.958 | Q12: =DATEDIF(M12,B12,"D") -> 245 | R12: =EOMONTH(B12,0) -> 45412 | T12: East
A13: TRX0015 | B13: 45440 | C13: CUST008 | D13: Jennifer Taylor | E13: P002 | F13: Smartphone | G13: Electronics | H13: 5 | I13: 699.99 | J13: PayPal | K13: West | L13: Standard | M13: 44407 | N13: =I13*H13 -> 3499.95 | O13: =TODAY() -> 46143 | P13: =NOW() -> 46143.958 | Q13: =DATEDIF(M13,B13,"D") -> 1033 | R13: =EOMONTH(B13,0) -> 45443 | T13: East
A14: TRX0173 | B14: 45581 | C14: CUST018 | D14: Barbara Young | E14: P002 | F14: Smartphone | G14: Electronics | H14: 5 | I14: 699.99 | J14: Cash | K14: East | L14: Standard | M14: 45008 | N14: =I14*H14 -> 3499.95 | O14: =TODAY() -> 46143 | P14: =NOW() -> 46143.958 | Q14: =DATEDIF(M14,B14,"D") -> 573 | R14: =EOMONTH(B14,0) -> 45596 | T14: East
... A49: TRX0009 | B49: 45588 | C49: CUST004 | D49: Sarah Davis | E49: P002 | F49: Smartphone | G49: Electronics | H49: 2 | I49: 699.99 | J49: Cash | K49: Central | L49: Basic | M49: 44992 | N49: =I49*H49 -> 1399.98 | O49: =TODAY() -> 46143 | P49: =NOW() -> 46143.958 | Q49: =DATEDIF(M49,B49,"D") -> 596 | R49: =EOMONTH(B49,0) -> 45596 | T49: East
A50: TRX0033 | B50: 45613 | C50: CUST025 | D50: Mark Carter | E50: P002 | F50: Smartphone | G50: Electronics | H50: 2 | I50: 699.99 | J50: PayPal | K50: West | L50: Standard | M50: 44770 | N50: =I50*H50 -> 1399.98 | O50: =TODAY() -> 46143 | P50: =NOW() -> 46143.958 | Q50: =DATEDIF(M50,B50,"D") -> 843 | R50: =EOMONTH(B50,0) -> 45626
A51: TRX0188 | B51: 45686 | C51: CUST045 | D51: Douglas Watson | E51: P002 | F51: Smartphone | G51: Electronics | H51: 2 | I51: 699.99 | J51: Debit Card | K51: Central | L51: Premium | M51: 44681 | N51: =I51*H51 -> 1399.98 | O51: =TODAY() -> 46143 | P51: =NOW() -> 46143.958 | Q51: =DATEDIF(M51,B51,"D") -> 1005 | R51: =EOMONTH(B51,0) -> 45688
A52: TRX0068 | B52: 45748 | C52: CUST044 | D52: Cynthia Price | E52: P002 | F52: Smartphone | G52: Electronics | H52: 2 | I52: 699.99 | J52: PayPal | K52: North | L52: Standard | M52: 44618 | N52: =I52*H52 -> 1399.98 | O52: =TODAY() -> 46143 | P52: =NOW() -> 46143.958 | Q52: =DATEDIF(M52,B52,"D") -> 1130 | R52: =EOMONTH(B52,0) -> 45777
A53: TRX0071 | B53: 45422 | C53: CUST036 | D53: Nancy Collins | E53: P009 | F53: Monitor | G53: Electronics | H53: 5 | I53: 249.99 | J53: Credit Card | K53: West | L53: Standard | M53: 44525 | N53: =I53*H53 -> 1249.95 | O53: =TODAY() -> 46143 | P53: =NOW() -> 46143.958 | Q53: =DATEDIF(M53,B53,"D") -> 897 | R53: =EOMONTH(B53,0) -> 45443
A54: TRX0234 | B54: 45449 | C54: CUST013 | D54: Joseph Jackson | E54: P009 | F54: Monitor | G54: Electronics | H54: 5 | I54: 249.99 | J54: Credit Card | K54: East | L54: Standard | M54: 44707 | N54: =I54*H54 -> 1249.95 | O54: =TODAY() -> 46143 | P54: =NOW() -> 46143.958 | Q54: =DATEDIF(M54,B54,"D") -> 742 | R54: =EOMONTH(B54,0) -> 45473
A55: TRX0075 | B55: 45517 | C55: CUST020 | D55: Margaret Wright | E55: P009 | F55: Monitor | G55: Electronics | H55: 5 | I55: 249.99 | J55: PayPal | K55: East | L55: Premium | M55: 44782 | N55: =I55*H55 -> 1249.95 | O55: =TODAY() -> 46143 | P55: =NOW() -> 46143.958 | Q55: =DATEDIF(M55,B55,"D") -> 735 | R55: =EOMONTH(B55,0) -> 45535
A56: TRX0057 | B56: 45597 | C56: CUST023 | D56: Paul Baker | E56: P009 | F56: Monitor | G56: Electronics | H56: 5 | I56: 249.99 | J56: Credit Card | K56: South | L56: Standard | M56: 44881 | N56: =I56*H56 -> 1249.95 | O56: =TODAY() -> 46143 | P56: =NOW() -> 46143.958 | Q56: =DATEDIF(M56,B56,"D") -> 716 | R56: =EOMONTH(B56,0) -> 45626
A57: TRX0012 | B57: 45622 | C57: CUST045 | D57: Douglas Watson | E57: P009 | F57: Monitor | G57: Electronics | H57: 5 | I57: 249.99 | J57: Credit Card | K57: North | L57: Basic | M57: 44873 | N57: =I57*H57 -> 1249.95 | O57: =TODAY() -> 46143 | P57: =NOW() -> 46143.958 | Q57: =DATEDIF(M57,B57,"D") -> 749 | R57: =EOMONTH(B57,0) -> 45626
A58: TRX0094 | B58: 45627 | C58: CUST017 | D58: Charles Allen | E58: P009 | F58: Monitor | G58: Electronics | H58: 5 | I58: 249.99 | J58: Cash | K58: Central | L58: Premium | M58: 44485 | N58: =I58*H58 -> 1249.95 | O58: =TODAY() -> 46143 | P58: =NOW() -> 46143.958 | Q58: =DATEDIF(M58,B58,"D") -> 1142 | R58: =EOMONTH(B58,0) -> 45657
A59: TRX0243 | B59: 45667 | C59: CUST048 | D59: Virginia Sanders | E59: P009 | F59: Monitor | G59: Electronics | H59: 5 | I59: 249.99 | J59: Credit Card | K59: South | L59: Basic | M59: 45330 | N59: =I59*H59 -> 1249.95 | O59: =TODAY() -> 46143 | P59: =NOW() -> 46143.958 | Q59: =DATEDIF(M59,B59,"D") -> 337 | R59: =EOMONTH(B59,0) -> 45688
A60: TRX0175 | B60: 45723 | C60: CUST030 | D60: Helen Roberts | E60: P009 | F60: Monitor | G60: Electronics | H60: 5 | I60: 249.99 | J60: Cash | K60: East | L60: Standard | M60: 44540 | N60: =I60*H60 -> 1249.95 | O60: =TODAY() -> 46143 | P60: =NOW() -> 46143.958 | Q60: =DATEDIF(M60,B60,"D") -> 1183 | R60: =EOMONTH(B60,0) -> 45747
A61: TRX0242 | B61: 45416 | C61: CUST025 | D61: Mark Carter | E61: P007 | F61: Desk | G61: Furniture | H61: 4 | I61: 299.99 | J61: Cash | K61: West | L61: Premium | M61: 44716 | N61: =I61*H61 -> 1199.96 | O61: =TODAY() -> 46143 | P61: =NOW() -> 46143.958 | Q61: =DATEDIF(M61,B61,"D") -> 700 | R61: =EOMONTH(B61,0) -> 45443
... A251: TRX0219 | B251: 45692 | C251: CUST037 | D251: Arthur Edwards | E251: P005 | F251: Blender | G251: Appliances | H251: 1 | I251: 59.99 | J251: Debit Card | K251: Central | L251: Standard | M251: 45045 | N251: =I251*H251 -> 59.99 | O251: =TODAY() -> 46143 | P251: =NOW() -> 46143.958 | Q251: =DATEDIF(M251,B251,"D") -> 647 | R251: =EOMONTH(B251,0) -> 45716

Sheet Sheet2
A1: - Use GroupBy concepts to find High-Value Customers using formulas
A2: =INDEX(Sheet1!$D$2:$D$252,MATCH(MAX(Sheet1!$N$2:$N$251),Sheet1!$N$2:$N$251,0)) -> Paul Baker
A4: - Find most frequently purchased product or repeating names using formulas
A5: {=INDEX(Sheet1!F2:F251,MODE(MATCH(Sheet1!E2:E251,Sheet1!E2:E251,0)))} -> Bookshelf
A7: Compare two lists and extract matching names in a new column
A8: Names_List_1 | B8: Names_List_2 | D8: Matching List
A9: Aarav | B9: Kabir | D9: =IF(COUNTIF($A$9:$A$20,B9)>0,B9,"NO MATCH") -> Kabir
A10: Vivaan | B10: Aryan | D10: =IF(COUNTIF($A$9:$A$20,B10)>0,B10,"NO MATCH") -> NO MATCH
A11: Aditya | B11: Sai | D11: =IF(COUNTIF($A$9:$A$20,B11)>0,B11,"NO MATCH") -> Sai
A12: Vihaan | B12: Rohan | D12: =IF(COUNTIF($A$9:$A$20,B12)>0,B12,"NO MATCH") -> Rohan
A13: Arjun | B13: Kunal | D13: =IF(COUNTIF($A$9:$A$20,B13)>0,B13,"NO MATCH") -> NO MATCH
A14: Sai | B14: Arjun | D14: =IF(COUNTIF($A$9:$A$20,B14)>0,B14,"NO MATCH") -> Arjun
A15: Reyansh | B15: Dhruv | D15: =IF(COUNTIF($A$9:$A$20,B15)>0,B15,"NO MATCH") -> NO MATCH
A16: Krishna | B16: Ishan | D16: =IF(COUNTIF($A$9:$A$20,B16)>0,B16,"NO MATCH") -> Ishan
A17: Ishan | B17: Om | D17: =IF(COUNTIF($A$9:$A$20,B17)>0,B17,"NO MATCH") -> NO MATCH
A18: Kabir | B18: Aditya | D18: =IF(COUNTIF($A$9:$A$20,B18)>0,B18,"NO MATCH") -> Aditya
A19: Rohan | B19: Brijesh | D19: =IF(COUNTIF($A$9:$A$20,B19)>0,B19,"NO MATCH") -> NO MATCH
A20: Dev | B20: Rajesh | D20: =IF(COUNTIF($A$9:$A$20,B20)>0,B20,"NO MATCH") -> NO MATCH
A22: - Create Abbreviations using TEXT functions
A23: {=_xlfn.TEXTJOIN("",TRUE,LEFT(_xlfn.TEXTSPLIT(Sheet1!D2," "),1))} -> PB
A24: {=_xlfn.TEXTJOIN("",TRUE,LEFT(_xlfn.TEXTSPLIT(Sheet1!D3," "),1))} -> EM
A25: {=_xlfn.TEXTJOIN("",TRUE,LEFT(_xlfn.TEXTSPLIT(Sheet1!D4," "),1))} -> JJ
A26: {=_xlfn.TEXTJOIN("",TRUE,LEFT(_xlfn.TEXTSPLIT(Sheet1!D5," "),1))} -> GM
A27: {=_xlfn.TEXTJOIN("",TRUE,LEFT(_xlfn.TEXTSPLIT(Sheet1!D6," "),1))} -> DK
A28: {=_xlfn.TEXTJOIN("",TRUE,LEFT(_xlfn.TEXTSPLIT(Sheet1!D7," "),1))} -> HM
A29: {=_xlfn.TEXTJOIN("",TRUE,LEFT(_xlfn.TEXTSPLIT(Sheet1!D8," "),1))} -> MC

Sheet Pivot Table
A1: Sum of Total_Amount | B1: Column Labels
A2: Row Labels | B2: Central | C2: East | D2: North | E2: South | F2: West | G2: Grand Total
A3: Appliances | B3: 1999.71 | C3: 2239.67 | D3: 1119.84 | E3: 1099.83 | F3: 1879.69 | G3: 8338.74
A4: Electronics | B4: 24889.33 | C4: 50649.01 | D4: 39239.04 | E4: 25549.32 | F4: 31429.35 | G4: 171756.05
A5: Furniture | B5: 14399.3 | C5: 6399.71 | D5: 10449.43 | E5: 9749.6 | F5: 8099.64 | G5: 49097.68
A6: Grand Total | B6: 41288.34 | C6: 59288.39 | D6: 50808.31 | E6: 36398.75 | F6: 41408.68 | G6: 229192.47
A9: Sum of Total_Amount | B9: Column Labels
A10: Row Labels | B10: Cash | C10: Credit Card | D10: Debit Card | E10: PayPal | F10: Grand Total
A11: Blender | B11: 2039.66 | C11: 779.87 | D11: 1739.71 | E11: 659.89 | F11: 5219.13
A12: Bookshelf | B12: 4799.68 | C12: 3899.74 | D12: 2699.82 | E12: 3899.74 | F12: 15298.98
A13: Coffee Maker | B13: 1199.85 | C13: 639.92 | D13: 959.88 | E13: 319.96 | F13: 3119.61
A14: Desk | B14: 8099.73 | C14: 8999.7 | D14: 3599.88 | E14: 2699.91 | F14: 23399.22
A15: Headphones | B15: 2249.85 | C15: 1649.89 | D15: 1499.9 | E15: 1649.89 | F15: 7049.53
A16: Keyboard | B16: 1439.84 | C16: 2429.73 | D16: 2069.77 | E16: 2069.77 | F16: 8009.11
A17: Laptop | B17: 8099.91 | C17: 16199.82 | D17: 20699.77 | E17: 22499.75 | F17: 67499.25
A18: Monitor | B18: 4499.82 | C18: 10749.57 | D18: 2249.91 | E18: 4499.82 | F18: 21999.12
A19: Office Chair | B19: 5399.73 | C19: 1399.93 | D19: 2599.87 | E19: 999.95 | F19: 10399.48
A20: Smartphone | B20: 19599.72 | C20: 14699.79 | D20: 13999.8 | E20: 18899.73 | F20: 67199.04
A21: Grand Total | B21: 57427.79 | C21: 61447.96 | D21: 52118.31 | E21: 58198.41 | F21: 229192.47
A23: Sum of Total_Amount | B23: Column Labels
A24: Row Labels | B24: Blender | C24: Bookshelf | D24: Coffee Maker | E24: Desk | F24: Headphones | G24: Keyboard | H24: Laptop | I24: Monitor | J24: Office Chair | K24: Smartphone | L24: Grand Total
A25: Basic | B25: 1139.81 | C25: 4949.67 | D25: 1679.79 | E25: 11699.61 | F25: 2099.86 | G25: 2159.76 | H25: 15299.83 | I25: 3749.85 | J25: 2599.87 | K25: 16799.76 | L25: 62177.81
A26: Premium | B26: 1379.77 | C26: 5999.6 | D26: 799.9 | E26: 5999.8 | F26: 2999.8 | G26: 4679.48 | H26: 17099.81 | I26: 9499.62 | J26: 3999.8 | K26: 32199.54 | L26: 84657.12
A27: Standard | B27: 2699.55 | C27: 4349.71 | D27: 639.92 | E27: 5699.81 | F27: 1949.87 | G27: 1169.87 | H27: 35099.61 | I27: 8749.65 | J27: 3799.81 | K27: 18199.74 | L27: 82357.54
A28: Grand Total | B28: 5219.13 | C28: 15298.98 | D28: 3119.61 | E28: 23399.22 | F28: 7049.53 | G28: 8009.11 | H28: 67499.25 | I28: 21999.12 | J28: 10399.48 | K28: 67199.04 | L28: 229192.47
A30: Sum of Total_Amount | B30: Column Labels
A31: Row Labels | B31: Central | C31: East | D31: North | E31: South | F31: West | G31: Grand Total
A32: Basic | B32: 16339.4 | C32: 9319.68 | D32: 14799.51 | E32: 10419.54 | F32: 11299.68 | G32: 62177.81
A33: Premium | B33: 15479.35 | C33: 26009.43 | D33: 26569.11 | E33: 6499.74 | F33: 10099.49 | G33: 84657.12
A34: Standard | B34: 9469.59 | C34: 23959.28 | D34: 9439.69 | E34: 19479.47 | F34: 20009.51 | G34: 82357.54
A35: Grand Total | B35: 41288.34 | C35: 59288.39 | D35: 50808.31 | E35: 36398.75 | F35: 41408.68 | G35: 229192.47

Sheet Dashboard
H1: Dashboard

Sheet Linear Regression
A1: Size (sq ft) | B1: Bedrooms(X) | C1: Age (Years) | D1: Price (₹ Lakhs) (Y)
A2: 800 | B2: 2 | C2: 10 | D2: 40 | I2: Calculation for Slope & Intercept
A3: 1000 | B3: 2 | C3: 8 | D3: 50 | I3: Mean (of X) | J3: Mean (of Y) | K3: Deviations (of X) | L3: Deviations (of Y) | M3: Product of Deviations | N3: Sum of Product of Deviations | O3: Square of Deviations (of X) | P3: Sum of Square of Deviations (of X)
A4: 1200 | B4: 3 | C4: 5 | D4: 60 | I4: =AVERAGE(B2:B6) -> 2.8 | J4: =AVERAGE(D2:D6) -> 59 | K4: =STDEV(B2,$B$2:$B$6) -> 0.81649658 | L4: =STDEV(D2,$D$2:$D$6) -> 15.625833 | M4: =K4*L4 -> 12.758439 | N4: =SUM(M4:M8) -> 59.177733 | O4: =K4*K4 -> 0.66666667 | P4: =SUM(O4:O8) -> 3.2666667
A5: 1500 | B5: 3 | C5: 7 | D5: 65 | K5: =STDEV(B3,$B$2:$B$6) -> 0.81649658 | L5: =STDEV(D3,$D$2:$D$6) -> 14.053469 | M5: =K5*L5 -> 11.47461 | O5: =K5*K5 -> 0.66666667
A6: 1800 | B6: 4 | C6: 6 | D6: 80 | K6: =STDEV(B4,$B$2:$B$6) -> 0.75277265 | L6: =STDEV(D4,$D$2:$D$6) -> 13.570802 | M6: =K6*L6 -> 10.215729 | O6: =K6*K6 -> 0.56666667
K7: =STDEV(B5,$B$2:$B$6) -> 0.75277265 | L7: =STDEV(D5,$D$2:$D$6) -> 13.784049 | M7: =K7*L7 -> 10.376255 | O7: =K7*K7 -> 0.56666667
A8: 2000 | B8: 4 | C8: 4 | D8: =$J$13*B8+$J$14 -> 80.738759 | K8: =STDEV(B6,$B$2:$B$6) -> 0.89442719 | L8: =STDEV(D6,$D$2:$D$6) -> 16.046807 | M8: =K8*L8 -> 14.3527 | O8: =K8*K8 -> 0.8
A9: 2200 | B9: 5 | C9: 3 | D9: =J14*I5+J15 -> 0
A10: 2500 | B10: 5 | C10: 2 | D10: =J15*I6+J16 -> 0 | I10: Slope (m) = Sum of Product of Deviations / Sum of Square of deviation for X
I11: Intercept (c) = Mean of Y - (m * Mean of X)
I13: M | J13: =N4/P4 -> 18.115632
I14: C | J14: =J4-(J13*I4) -> 8.276229
I17: Slope (m) = | J17: =SLOPE(D2:D6,B2:B6) -> 17.5
I18: Intercept (c) = | J18: =INTERCEPT(D2:D6,B2:B6) -> 10

Sheet WhatIf
A1: Parameter | B1: Value
A2: Selling Price/unit | B2: 600
A3: Cost Price/unit | B3: 300
A4: Fixed Costs | B4: 20000
A5: Units Sold | B5: 143.33333
A6: Profit | B6: =(B5*(B2-B3)) - B4 -> 23000
